ultimatesmoother.py
ultimatesmoother-1.0.0.dist-info/METADATA
ultimatesmoother-1.0.0.dist-info/WHEEL
ultimatesmoother-1.0.0.dist-info/licenses/LICENSE
ultimatesmoother-1.0.0.dist-info/RECORD
