Metadata-Version: 2.4
Name: ultimatesmoother
Version: 1.0.0
Summary: The UltimateSmoother preserves low-frequency swings in the input time series while attenuating high-frequency variations and noise.
Project-URL: Homepage, https://github.com/pcktm/ultimatesmoother
Project-URL: Issues, https://github.com/pcktm/ultimatesmoother/issues
Author-email: pcktm <hi@kopanko.com>
License-File: LICENSE
Keywords: band-pass,band-stop,filtering,high-pass,low-pass,smoothing,time series
Classifier: Development Status :: 5 - Production/Stable
Classifier: Intended Audience :: Developers
Classifier: Intended Audience :: Science/Research
Classifier: License :: OSI Approved :: MIT License
Classifier: Programming Language :: Python :: 3
Classifier: Programming Language :: Python :: 3.8
Classifier: Programming Language :: Python :: 3.9
Classifier: Programming Language :: Python :: 3.10
Classifier: Programming Language :: Python :: 3.11
Classifier: Topic :: Scientific/Engineering
Classifier: Topic :: Software Development
Classifier: Topic :: Software Development :: Libraries
Classifier: Topic :: Software Development :: Libraries :: Python Modules
Classifier: Topic :: Utilities
Requires-Python: >=3.8
Requires-Dist: numpy>=1.24.4
